me_backup/__init__.py
me_backup/__main__.py
me_backup/backup.py
me_backup/cli.py
me_backup/config.py
me_backup/crontab.py
me_backup/data.py
me_backup/definitions.py
me_backup/install.py
me_backup/log.py
me_backup/task.py
me_backup/task_example.yaml
me_backup/utils.py
me_backup/wake_on_lan.py
me_backup-0.1.24.dist-info/WHEEL
me_backup-0.1.24.dist-info/METADATA
me_backup-0.1.24.dist-info/RECORD
