Metadata-Version: 2.1
Name: me-backup
Version: 0.1.24
Summary: Simple linux backup controled by a YAML file.
Home-page: https://github.com/lbmello/me-backup
Author: Lucas
Author-email: lucasbmello96@gmail.com
Requires-Python: >=3.9,<4.0
Classifier: Programming Language :: Python :: 3
Classifier: Programming Language :: Python :: 3.10
Classifier: Programming Language :: Python :: 3.9
Requires-Dist: PyYAML
Requires-Dist: click (>=8.0.1,<9.0.0)
Requires-Dist: python-crontab (>=2.5.1,<3.0.0)
Requires-Dist: pythonping (>=1.1.1,<2.0.0)
Requires-Dist: wakeonlan (>=2.0.1,<3.0.0)
Project-URL: Repository, https://github.com/lbmello/me-backup
